xhsaliyunmcpserver/__init__.py
xhsaliyunmcpserver/server.py
xhsaliyunmcpserver-0.1.0.dist-info/WHEEL
xhsaliyunmcpserver-0.1.0.dist-info/entry_points.txt
xhsaliyunmcpserver-0.1.0.dist-info/METADATA
xhsaliyunmcpserver-0.1.0.dist-info/RECORD
