Metadata-Version: 2.3
Name: xhsaliyunmcpserver
Version: 0.1.0
Summary: Add your description here
Author: gaomin
Author-email: gaomin <gaomin@huizhihuyu.com>
Requires-Dist: bs4>=0.0.2
Requires-Dist: dashscope>=1.24.5
Requires-Dist: dotenv>=0.9.9
Requires-Dist: httpx>=0.28.1
Requires-Dist: mcp[cli]>=1.14.1
Requires-Python: >=3.10
